bottle_log.py
bottle_log-1.0.0.dist-info/DESCRIPTION.rst
bottle_log-1.0.0.dist-info/LICENSE.txt
bottle_log-1.0.0.dist-info/METADATA
bottle_log-1.0.0.dist-info/RECORD
bottle_log-1.0.0.dist-info/WHEEL
bottle_log-1.0.0.dist-info/metadata.json
bottle_log-1.0.0.dist-info/top_level.txt
