Metadata-Version: 2.0
Name: bottle-log
Version: 1.0.0
Summary: Improved logging for Bottle.
Home-page: https://github.com/romabysen/bottle-log
Author: Lars Hansson
Author-email: romabysen@gmail.com
License: New BSD
Platform: UNKNOWN
Classifier: Development Status :: 5 - Production/Stable
Classifier: Intended Audience :: Developers
Classifier: Environment :: Web Environment
Classifier: Operating System :: OS Independent
Classifier: Programming Language :: Python :: 2.7
Classifier: Programming Language :: Python :: 3
Classifier: Topic :: Software Development :: Libraries :: Python Modules
Classifier: Framework :: Bottle
Classifier: License :: OSI Approved :: BSD License
Requires-Dist: bottle (>=0.10.0)
